ipspot/__init__.py
ipspot/__main__.py
ipspot/cli.py
ipspot/ipv4.py
ipspot/ipv6.py
ipspot/params.py
ipspot/utils.py
ipspot-0.7.dist-info/licenses/AUTHORS.md
ipspot-0.7.dist-info/licenses/LICENSE
ipspot-0.7.dist-info/METADATA
ipspot-0.7.dist-info/WHEEL
ipspot-0.7.dist-info/entry_points.txt
ipspot-0.7.dist-info/top_level.txt
ipspot-0.7.dist-info/RECORD
